pinscrap/__init__.py
pinscrap/client.py
pinscrap/exceptions.py
pinscrap/models.py
pinscrap/utils.py
pinscrap-0.1.1.dist-info/METADATA
pinscrap-0.1.1.dist-info/WHEEL
pinscrap-0.1.1.dist-info/top_level.txt
pinscrap-0.1.1.dist-info/RECORD
