Metadata-Version: 2.4
Name: pinscrap
Version: 0.1.1
Summary: Una biblioteca avanzada para extraer datos de Pinterest sin necesidad de API
Author-email: Patchyn <kaitonekox@outlook.com>
License: MIT
Project-URL: Homepage, https://github.com/patchyn/pinscrap
Project-URL: Documentation, https://pinscrap.workers.dev/docs
Project-URL: Repository, https://github.com/patchyn/pinscrap
Project-URL: Changelog, https://github.com/patchyn/pinscrap/blob/main/CHANGELOG.md
Project-URL: Issues, https://github.com/patchyn/pinscrap/issues
Classifier: Development Status :: 4 - Beta
Classifier: Intended Audience :: Developers
Classifier: License :: OSI Approved :: MIT License
Classifier: Programming Language :: Python :: 3.8
Classifier: Programming Language :: Python :: 3.9
Classifier: Programming Language :: Python :: 3.10
Classifier: Programming Language :: Python :: 3.11
Classifier: Programming Language :: Python :: 3.12
Classifier: Operating System :: OS Independent
Classifier: Framework :: AsyncIO
Classifier: Topic :: Internet :: WWW/HTTP :: Browsers
Classifier: Topic :: Software Development :: Libraries :: Python Modules
Classifier: Topic :: Utilities
Requires-Python: >=3.8
Requires-Dist: aiohttp>=3.8.0
Requires-Dist: aiofiles>=23.1.0
Requires-Dist: playwright>=1.40.0
Requires-Dist: pydantic>=2.5.0
Requires-Dist: loguru>=0.7.0
Requires-Dist: typing-extensions>=4.0.0; python_version < "3.10"
Provides-Extra: dev
Requires-Dist: pytest>=7.0.0; extra == "dev"
Requires-Dist: pytest-asyncio>=0.21.0; extra == "dev"
Requires-Dist: pytest-cov>=4.0.0; extra == "dev"
Requires-Dist: black>=23.0.0; extra == "dev"
Requires-Dist: isort>=5.12.0; extra == "dev"
Requires-Dist: mypy>=1.0.0; extra == "dev"
Requires-Dist: flake8>=6.0.0; extra == "dev"
